startt/__init__.py
startt/analyze.py
startt/process.py
startt-0.16.0.data/scripts/startt
startt-0.16.0.dist-info/METADATA
startt-0.16.0.dist-info/WHEEL
startt-0.16.0.dist-info/namespace_packages.txt
startt-0.16.0.dist-info/top_level.txt
startt-0.16.0.dist-info/zip-safe
startt-0.16.0.dist-info/RECORD
